investpy/__init__.py
investpy/calculos.py
investpy/core.py
investpy/dados.py
investpy/visualizacao.py
iissa_investimentpy-1.0.0.dist-info/METADATA
iissa_investimentpy-1.0.0.dist-info/WHEEL
iissa_investimentpy-1.0.0.dist-info/top_level.txt
iissa_investimentpy-1.0.0.dist-info/RECORD
