Metadata-Version: 2.1
Name: iissa-investimentpy
Version: 1.0.0
Summary: Uma biblioteca para análise de investimentos
Home-page: https://github.com/ivanissa/investimentpy
Author: Ivan Alfredo Issa
Author-email: ivanissa.dev@gmail.com
License: MIT
Platform: UNKNOWN
